geo_factory.py
geo_factory-1.0.0.dist-info/LICENSE
geo_factory-1.0.0.dist-info/METADATA
geo_factory-1.0.0.dist-info/WHEEL
geo_factory-1.0.0.dist-info/entry_points.txt
geo_factory-1.0.0.dist-info/top_level.txt
geo_factory-1.0.0.dist-info/RECORD
