Metadata-Version: 2.1
Name: geo-factory
Version: 1.0.0
Summary: 一个能操作GEO MINiML formatted family文件的Python工具（A Python tool that can manipulate GEO MINiML formatted files）
Home-page: https://github.com/taishengxin/geo-factory
Author: TaiShengXin
Author-email: taishengxin@gmail.com
License: MIT
Platform: UNKNOWN
Classifier: License :: OSI Approved :: MIT License
Classifier: Programming Language :: Python
Classifier: Programming Language :: Python :: 3
Classifier: Programming Language :: Python :: 3.6
Classifier: Programming Language :: Python :: Implementation :: CPython
Classifier: Programming Language :: Python :: Implementation :: PyPy
Classifier: Topic :: Scientific/Engineering :: Bio-Informatics
Requires-Python: >=3.6.0
Requires-Dist: click
Requires-Dist: pandas
Requires-Dist: xmltodict
